{
  "version": "7",
  "dialect": "sqlite",
  "entries": [
    {
      "idx": 0,
      "version": "6",
      "when": 1772484813856,
      "tag": "0000_initial_schema",
      "breakpoints": true
    },
    {
      "idx": 1,
      "version": "6",
      "when": 1772484900000,
      "tag": "0001_add_api_sources",
      "breakpoints": true
    },
    {
      "idx": 2,
      "version": "6",
      "when": 1772485000000,
      "tag": "0002_add_scan_folders",
      "breakpoints": true
    },
    {
      "idx": 3,
      "version": "6",
      "when": 1772639750778,
      "tag": "0003_add_movie_drafts",
      "breakpoints": true
    },
    {
      "idx": 4,
      "version": "6",
      "when": 1772640000000,
      "tag": "0004_add_movies_watched",
      "breakpoints": true
    },
    {
      "idx": 5,
      "version": "6",
      "when": 1772811215914,
      "tag": "0005_add_movies_watched_at",
      "breakpoints": true
    }
  ]
}